parsing_lawsuits/python_callables.py
lawsuitssubsystem-0.1.0.dist-info/METADATA
lawsuitssubsystem-0.1.0.dist-info/WHEEL
lawsuitssubsystem-0.1.0.dist-info/RECORD
